{
    "MlibObjs": {},
    "PrevCompiledModules": {
        "tb_mux_delay": {
            "uuixR_d": {
                "checksum": 0,
                "bytes": 184142,
                "mod": "tb_mux_delay",
                "archive": "archive.6/_10908_archive_1.a",
                "out": "uuixR_d.o",
                "mode": 4
            }
        },
        "math_pkg": {
            "aG6Rf_d": {
                "checksum": 0,
                "bytes": 10418,
                "mod": "math_pkg",
                "archive": "archive.6/_10908_archive_1.a",
                "out": "aG6Rf_d.o",
                "mode": 4
            }
        },
        "XMODEL_global": {
            "w8VQw_d": {
                "checksum": 0,
                "bytes": 17887,
                "mod": "XMODEL_global",
                "mode": 4,
                "out": "w8VQw_d.o",
                "archive": "archive.6/_10908_archive_1.a"
            }
        },
        "bit_to_xreal": {
            "VSICe_d": {
                "checksum": 0,
                "bytes": 45533,
                "mod": "bit_to_xreal",
                "archive": "archive.6/_10908_archive_1.a",
                "out": "VSICe_d.o",
                "mode": 4
            }
        },
        "trig_time": {
            "uTRJL_d": {
                "checksum": 0,
                "bytes": 29234,
                "mod": "trig_time",
                "mode": 4,
                "out": "uTRJL_d.o",
                "archive": "archive.6/_10908_archive_1.a"
            }
        },
        "trig_cross": {
            "mzR8J_d": {
                "checksum": 0,
                "bytes": 25289,
                "mod": "trig_cross",
                "mode": 4,
                "out": "mzR8J_d.o",
                "archive": "archive.6/_10908_archive_1.a"
            }
        },
        "std": {
            "reYIK_d": {
                "checksum": 0,
                "bytes": 33296,
                "mod": "std",
                "mode": 4,
                "out": "reYIK_d.o",
                "archive": "archive.6/_prev_archive_1.a"
            }
        },
        "xmodel_prims": {
            "nRDma_d": {
                "checksum": 0,
                "bytes": 84778,
                "mod": "xmodel_prims",
                "archive": "archive.6/_10908_archive_1.a",
                "out": "nRDma_d.o",
                "mode": 4
            }
        },
        "xmodel_pkg": {
            "xpQjW_d": {
                "checksum": 0,
                "bytes": 28898,
                "mod": "xmodel_pkg",
                "archive": "archive.6/_10908_archive_1.a",
                "out": "xpQjW_d.o",
                "mode": 4
            }
        },
        "xreal_to_xbit_var_0000": {
            "tWQzP_d": {
                "checksum": 0,
                "bytes": 41938,
                "mod": "xreal_to_xbit_var_0000",
                "archive": "archive.6/_10908_archive_1.a",
                "out": "tWQzP_d.o",
                "mode": 4
            }
        },
        "...MASTER...": {
            "amcQw_d": {
                "checksum": 0,
                "bytes": 8193,
                "mod": "...MASTER...",
                "mode": 4,
                "out": "objs/amcQw_d.o"
            }
        }
    },
    "NameTable": {
        "_vcs_unit__1464944897": [
            "_vcs_unit__1464944897",
            "pECtM",
            "module"
        ],
        "trig_time": [
            "trig_time",
            "uTRJL",
            "module"
        ],
        "std": [
            "std",
            "reYIK",
            "module"
        ],
        "xmodel_pkg": [
            "xmodel_pkg",
            "xpQjW",
            "module"
        ],
        "xmodel_prims": [
            "xmodel_prims",
            "nRDma",
            "module"
        ],
        "math_pkg": [
            "math_pkg",
            "aG6Rf",
            "module"
        ],
        "XMODEL_global": [
            "XMODEL_global",
            "w8VQw",
            "module"
        ],
        "trig_cross": [
            "trig_cross",
            "mzR8J",
            "module"
        ],
        "bit_to_xreal": [
            "bit_to_xreal",
            "VSICe",
            "module"
        ],
        "xreal_to_xbit_var_0000": [
            "xreal_to_xbit_var_0000",
            "tWQzP",
            "module"
        ],
        "tb_mux_delay": [
            "tb_mux_delay",
            "uuixR",
            "module"
        ],
        "switch_0000": [
            "switch_0000",
            "DE7Kd",
            "module"
        ],
        "mux_RC": [
            "mux_RC",
            "tU03t",
            "module"
        ],
        "...MASTER...": [
            "SIM",
            "amcQw",
            "module"
        ]
    },
    "CurCompileModules": [
        "...MASTER...",
        "...MASTER...",
        "_vcs_unit__1464944897",
        "_vcs_unit__1464944897",
        "std",
        "xmodel_pkg",
        "xmodel_pkg",
        "xmodel_prims",
        "xmodel_prims",
        "math_pkg",
        "math_pkg",
        "XMODEL_global",
        "XMODEL_global",
        "trig_cross",
        "trig_cross",
        "trig_time",
        "trig_time",
        "bit_to_xreal",
        "bit_to_xreal",
        "xreal_to_xbit_var_0000",
        "xreal_to_xbit_var_0000",
        "switch_0000",
        "switch_0000",
        "mux_RC",
        "mux_RC",
        "tb_mux_delay",
        "tb_mux_delay"
    ],
    "stat": {
        "ru_self_cgstart": {
            "ru_utime_sec": 0.41599999999999998,
            "ru_nivcsw": 5,
            "ru_majflt": 0,
            "ru_minflt": 7852,
            "ru_stime_sec": 0.024,
            "ru_maxrss_kb": 97988,
            "ru_nvcsw": 45
        },
        "ru_childs_cgstart": {
            "ru_utime_sec": 0.0,
            "ru_nivcsw": 0,
            "ru_majflt": 0,
            "ru_minflt": 0,
            "ru_stime_sec": 0.0,
            "ru_maxrss_kb": 0,
            "ru_nvcsw": 0
        },
        "ru_childs_end": {
            "ru_utime_sec": 0.0,
            "ru_nivcsw": 2,
            "ru_majflt": 0,
            "ru_minflt": 202,
            "ru_stime_sec": 0.0,
            "ru_maxrss_kb": 27988,
            "ru_nvcsw": 1
        },
        "mopSpeed": 174142.85714285716,
        "nMops": 29256,
        "ru_self_end": {
            "ru_utime_sec": 0.58399999999999996,
            "ru_nivcsw": 6,
            "ru_majflt": 0,
            "ru_minflt": 11621,
            "ru_stime_sec": 0.035999999999999997,
            "ru_maxrss_kb": 106284,
            "ru_nvcsw": 46
        },
        "quadSpeed": 65755.952380952382,
        "totalObjSize": 715512,
        "CodeGen(%)": 28.767123287671229,
        "nQuads": 11047,
        "mop/quad": 2.6483208110799312,
        "outputSizePerQuad": 64.0,
        "Frontend(%)": 71.232876712328775
    },
    "CompileStrategy": "fullobj",
    "CurCompileUdps": {},
    "LVLData": [
        "SIM"
    ],
    "SIMBData": {
        "out": "amcQwB.o",
        "bytes": 72031
    },
    "Misc": {
        "default_output_dir": "csrc",
        "csrc_abs": "/home/group05/old_mux/csrc",
        "cwd": "/home/group05/old_mux",
        "daidir_abs": "/home/group05/old_mux/simv.daidir",
        "csrc": "csrc",
        "daidir": "/home/group05/old_mux/./simv.daidir",
        "archive_dir": "archive.6"
    },
    "PEModules": [],
    "CompileProcesses": [
        "cgproc.10908.json"
    ],
    "CompileStatus": "Successful"
}